{
  "project_info": {
    "project_number": "1036113362614",
    "project_id": "mess-management-250df",
    "storage_bucket": "mess-management-250df.firebasestorage.app"
  },
  "client": [
    {
      "client_info": {
        "mobilesdk_app_id": "1:1036113362614:android:26fae9214bdd7ee883b017",
        "android_client_info": {
          "package_name": "com.example.cse_connect"
        }
      },
      "oauth_client": [
        {
          "client_id": "1036113362614-j7f3i264eh8vb4puk6mvip9am4mik0sb.apps.googleusercontent.com",
          "client_type": 1,
          "android_info": {
            "package_name": "com.example.cse_connect",
            "certificate_hash": "1141bef8ff8014b950f6554a62094f5f761240bc"
          }
        },
        {
          "client_id": "1036113362614-p0836jimjvqqa04gmjaf1vi7vjnfndmf.apps.googleusercontent.com",
          "client_type": 3
        }
      ],
      "api_key": [
        {
          "current_key": "AIzaSyBo8wm0iTfAhqLT-zmtSNk9rIkHJtj_Z5s"
        }
      ],
      "services": {
        "appinvite_service": {
          "other_platform_oauth_client": [
            {
              "client_id": "1036113362614-p0836jimjvqqa04gmjaf1vi7vjnfndmf.apps.googleusercontent.com",
              "client_type": 3
            },
            {
              "client_id": "1036113362614-7968kuher5didbf0on55gahse7phaobs.apps.googleusercontent.com",
              "client_type": 2,
              "ios_info": {
                "bundle_id": "com.example.cseConnect"
              }
            }
          ]
        }
      }
    },
    {
      "client_info": {
        "mobilesdk_app_id": "1:1036113362614:android:f4802b93a6cbe1b883b017",
        "android_client_info": {
          "package_name": "com.example.messmanagement"
        }
      },
      "oauth_client": [
        {
          "client_id": "1036113362614-24ui87l4ta9sikft8efd2e71ufl4uj82.apps.googleusercontent.com",
          "client_type": 1,
          "android_info": {
            "package_name": "com.example.messmanagement",
            "certificate_hash": "1141bef8ff8014b950f6554a62094f5f761240bc"
          }
        },
        {
          "client_id": "1036113362614-d0voiqmc24adpl11fvplqufifrn2msse.apps.googleusercontent.com",
          "client_type": 1,
          "android_info": {
            "package_name": "com.example.messmanagement",
            "certificate_hash": "1f88c1444294bdde0756ddf4eeef5f8284d868e8"
          }
        },
        {
          "client_id": "1036113362614-p0836jimjvqqa04gmjaf1vi7vjnfndmf.apps.googleusercontent.com",
          "client_type": 3
        }
      ],
      "api_key": [
        {
          "current_key": "AIzaSyBo8wm0iTfAhqLT-zmtSNk9rIkHJtj_Z5s"
        }
      ],
      "services": {
        "appinvite_service": {
          "other_platform_oauth_client": [
            {
              "client_id": "1036113362614-p0836jimjvqqa04gmjaf1vi7vjnfndmf.apps.googleusercontent.com",
              "client_type": 3
            },
            {
              "client_id": "1036113362614-7968kuher5didbf0on55gahse7phaobs.apps.googleusercontent.com",
              "client_type": 2,
              "ios_info": {
                "bundle_id": "com.example.cseConnect"
              }
            }
          ]
        }
      }
    }
  ],
  "configuration_version": "1"
}